fmo/__init__.py
fmo/api.py
fmo/bed.py
fmo/lease.py
fmo/nmea.py
fmo/utils.py
fmo/cli/__init__.py
fmo/cli/beds.py
fmo/cli/deprecated.py
fmo/cli/lease.py
fmo/cli/logs.py
fmo/cli/simulator.py
fmo/draw/__init__.py
fmo/simulate/__init__.py
fmo/simulate/bcurve.py
fmo/simulate/circle.py
fmo/simulate/path_gen.py
fmo_cli-1.2.0.dist-info/METADATA
fmo_cli-1.2.0.dist-info/WHEEL
fmo_cli-1.2.0.dist-info/entry_points.txt
fmo_cli-1.2.0.dist-info/top_level.txt
fmo_cli-1.2.0.dist-info/RECORD
