Metadata-Version: 2.1
Name: fmo-cli
Version: 1.2.0
Summary: Command Line Interface to access and upload FindMyOyster data
Author: Gudjon Magnusson
Author-email: gmagnusson@fraunhofer.org
Keywords: FindMyOyster,CLI
Requires-Python: >=3.7, <4
Requires-Dist: click>=8.0.0
Requires-Dist: pandas>=2.0.0
Requires-Dist: requests>=2.28.2
Requires-Dist: python-dotenv>=1.0.0
Requires-Dist: geojson>=3.0.1
